HISTORY.rst
LICENSE
MANIFEST.in
README.rst
README_CH.rst
VERSION
requirements.txt
setup.py
FishFishJump.egg-info/PKG-INFO
FishFishJump.egg-info/SOURCES.txt
FishFishJump.egg-info/dependency_links.txt
FishFishJump.egg-info/entry_points.txt
FishFishJump.egg-info/requires.txt
FishFishJump.egg-info/top_level.txt
fish_core/__init__.py
fish_core/bloomfilter.py
fish_core/default.py
fish_core/search_engine.py
fish_core/simhash.py
fish_core/scrapy/__init__.py
fish_core/scrapy/extensions.py
fish_core/scrapy/items.py
fish_core/scrapy/pipelines.py
fish_core/scrapy/run_crawler.py
fish_core/utils/__init__.py
fish_core/utils/common_utils.py
fish_core/utils/http_utils.py
fish_core/utils/mail_utils.py
fish_crawlers/Dockerfile
fish_crawlers/docker-compose.yml
fish_crawlers/requirements.txt
fish_crawlers/scrapyd.conf
fish_crawlers/dbs/README
fish_crawlers/eggs/README
fish_crawlers/items/README
fish_crawlers/logs/README
fish_crawlers/master_crawler/scrapy.cfg
fish_crawlers/master_crawler/master_crawler/__init__.py
fish_crawlers/master_crawler/master_crawler/items.py
fish_crawlers/master_crawler/master_crawler/middlewares.py
fish_crawlers/master_crawler/master_crawler/pipelines.py
fish_crawlers/master_crawler/master_crawler/settings.py
fish_crawlers/master_crawler/master_crawler/spiders/__init__.py
fish_crawlers/master_crawler/master_crawler/spiders/crawler.py
fish_crawlers/slave_crawler/scrapy.cfg
fish_crawlers/slave_crawler/slave_crawler/__init__.py
fish_crawlers/slave_crawler/slave_crawler/items.py
fish_crawlers/slave_crawler/slave_crawler/middlewares.py
fish_crawlers/slave_crawler/slave_crawler/pipelines.py
fish_crawlers/slave_crawler/slave_crawler/settings.py
fish_crawlers/slave_crawler/slave_crawler/spiders/__init__.py
fish_crawlers/slave_crawler/slave_crawler/spiders/crawler.py
fish_dashboard/Dockerfile
fish_dashboard/app.py
fish_dashboard/cache.py
fish_dashboard/cli.py
fish_dashboard/docker-compose.yml
fish_dashboard/fault.py
fish_dashboard/requirements.txt
fish_dashboard/settings.py
fish_dashboard/scrapyd/__init__.py
fish_dashboard/scrapyd/model.py
fish_dashboard/scrapyd/scrapyd_agent.py
fish_dashboard/scrapyd/scrapyd_db.py
fish_dashboard/scrapyd/scrapyd_service.py
