Metadata-Version: 1.1
Name: FishFishJump
Version: 0.2.3
Summary: FishFishJump is a solution that simply and basic for search engines and provide multiple demos that independent deployment by used Docker.
Home-page: https://github.com/SylvanasSun/FishFishJump
Author: SylvanasSun
Author-email: sylvanas.sun@gmail.com
License: MIT
Keywords: FishFishJump python scrapy scrapy-redis search engines
Platform: UNKNOWN
Classifier: Development Status :: 4 - Beta
Classifier: Intended Audience :: Developers
Classifier: License :: OSI Approved :: MIT License
Classifier: Programming Language :: Python :: 3.4
Classifier: Programming Language :: Python :: 3.5
Classifier: Programming Language :: Python :: 3.6
